inception/__init__.py
inception/client.py
inception/main.py
inception-0.1.0.dist-info/METADATA
inception-0.1.0.dist-info/WHEEL
inception-0.1.0.dist-info/entry_points.txt
inception-0.1.0.dist-info/RECORD
