Metadata-Version: 2.3
Name: inception
Version: 0.1.0
Summary: Python client and CLI for the Inception AI API
Requires-Python: >=3.12,<4.0
Classifier: Programming Language :: Python :: 3
Classifier: Programming Language :: Python :: 3.12
Classifier: Programming Language :: Python :: 3.13
Requires-Dist: click (>=8.0.0)
Requires-Dist: httpx (>=0.24.0)
Requires-Dist: platformdirs (>=3.0.0)
Requires-Dist: playwright (>=1.50.0,<2.0.0)
Requires-Dist: pydantic (>=2.0.0)
Requires-Dist: python-dotenv (>=1.0.1,<2.0.0)
Requires-Dist: rich (>=13.0.0)
Requires-Dist: sseclient-py (>=1.8.0)
Requires-Dist: typing-extensions (>=4.5.0)
